clipin/__init__.py
clipin/__myinit__.py
clipin/win_dib.py
clipin-1.0.0.dist-info/licenses/LICENSE
clipin-1.0.0.dist-info/METADATA
clipin-1.0.0.dist-info/WHEEL
clipin-1.0.0.dist-info/RECORD
