Metadata-Version: 2.4
Name: clipin
Version: 1.0.0
Summary: A zero-dependency cross-platform clipboard utility for Python.
License: MIT
License-File: LICENSE
Keywords: clipboard,cross-platform,utility,cli
Author: https://github.com/nunobrum
Requires-Python: >=3.7,<4.0
Classifier: License :: OSI Approved :: MIT License
Classifier: Programming Language :: Python :: 3
Classifier: Programming Language :: Python :: 3.7
Classifier: Programming Language :: Python :: 3.8
Classifier: Programming Language :: Python :: 3.9
Classifier: Programming Language :: Python :: 3.10
Classifier: Programming Language :: Python :: 3.11
Classifier: Programming Language :: Python :: 3.12
Classifier: Programming Language :: Python :: 3.13
Classifier: Programming Language :: Python :: 3.14
Project-URL: bug-tracker, https://github.com/nunobrum/clipin/issues
Project-URL: homepage, https://github.com/nunobrum/clipin
Project-URL: repository, https://github.com/nunobrum/clipin.git
